bmi_demo/__init__.py
bmi_demo/bmi.py
bmi_demo/cli.py
bmi_demo-1.0.0.dist-info/entry_points.txt
bmi_demo-1.0.0.dist-info/WHEEL
bmi_demo-1.0.0.dist-info/METADATA
bmi_demo-1.0.0.dist-info/RECORD
